{"cities": {"Bellefonte town, Delaware": {"ori": null, "total_arrests": 0, "note": "no_agency_match"}, "Bethany Beach town, Delaware": {"total_arrests": 48, "sex": {"Male": 42, "Female": 6}, "race": {"Asian": 0, "White": 40, "Unknown": 2, "Multiple": 0, "Not Specified": 0, "Black or African American": 6, "American Indian or Alaska Native": 0, "Native Hawaiian or Other Pacific Islander": 0, "Asian, Native Hawaiian, or Other Pacific Islander": 0}, "offenses": {"All Other Offenses": 17, "Larceny": 9, "Liquor Law Violations": 9, "Drug Possession": 4, "Disorderly Conduct": 3, "Vandalism": 2, "Simple Assault": 1, "Aggravated Assault": 1, "Drug Sale/Manufacturing": 1, "Drive Under the Influence": 1}, "offense_categories": {"All Other Offenses": 17, "Larceny": 9, "Liquor Law Violations": 9, "Drug/Narcotic Offenses": 5, "Disorderly Conduct": 3, "Destruction/Damage/Vandalism of Property": 2, "Simple Assault": 1, "Aggravated Assault": 1, "Drive Under the Influence": 1}, "year": "2022", "ori": "DE0031000", "city": "Bethany Beach town, Delaware"}, "Bethel town, Delaware": {"ori": null, "total_arrests": 0, "note": "skipped_small_population"}, "Blades town, Delaware": {"total_arrests": 24, "sex": {"Male": 15, "Female": 9}, "race": {"Asian": 0, "White": 18, "Unknown": 0, "Multiple": 0, "Not Specified": 0, "Black or African American": 6, "American Indian or Alaska Native": 0, "Native Hawaiian or Other Pacific Islander": 0, "Asian, Native Hawaiian, or Other Pacific Islander": 0}, "offenses": {"All Other Offenses": 6, "Simple Assault": 5, "Aggravated Assault": 5, "Larceny": 2, "Burglary": 2, "Counterfeiting/Forgery": 2, "Vandalism": 1, "Drug Possession": 1}, "offense_categories": {"All Other Offenses": 6, "Simple Assault": 5, "Aggravated Assault": 5, "Larceny": 2, "Burglary": 2, "Counterfeiting/Forgery": 2, "Drug/Narcotic Offenses": 1, "Destruction/Damage/Vandalism of Property": 1}, "year": "2022", "ori": "DE0030900", "city": "Blades town, Delaware"}, "Bowers town, Delaware": {"ori": null, "total_arrests": 0, "note": "skipped_small_population"}, "Bridgeville town, Delaware": {"total_arrests": 57, "sex": {"Male": 48, "Female": 9}, "race": {"Asian": 0, "White": 29, "Unknown": 1, "Multiple": 0, "Not Specified": 0, "Black or African American": 27, "American Indian or Alaska Native": 0, "Native Hawaiian or Other Pacific Islander": 0, "Asian, Native Hawaiian, or Other Pacific Islander": 0}, "offenses": {"Simple Assault": 13, "All Other Offenses": 8, "Burglary": 5, "Drug Possession": 5, "Aggravated Assault": 4, "Fraud": 3, "Weapons": 3, "Vandalism": 3, "Drug Sale/Manufacturing": 3, "Drive Under the Influence": 3, "Larceny": 2, "Stolen Property": 1, "Disorderly Conduct": 1, "Motor Vehicle Theft": 1, "Manslaughter by Negligence": 1, "Offenses Against the Family and Children": 1}, "offense_categories": {"Simple Assault": 13, "All Other Offenses": 8, "Drug/Narcotic Offenses": 8, "Burglary": 5, "Aggravated Assault": 4, "Fraud Offenses": 3, "Weapon Law Violations": 3, "Drive Under the Influence": 3, "Destruction/Damage/Vandalism of Property": 3, "Larceny": 2, "Homicide Offenses": 1, "Disorderly Conduct": 1, "Motor Vehicle Theft": 1, "Stolen Property Offenses": 1, "Family Offenses, Nonviolent": 1}, "year": "2022", "ori": "DE0030100", "city": "Bridgeville town, Delaware"}, "Camden town, Delaware": {"total_arrests": 163, "sex": {"Male": 106, "Female": 57}, "race": {"Asian": 1, "White": 86, "Unknown": 1, "Multiple": 0, "Not Specified": 0, "Black or African American": 75, "American Indian or Alaska Native": 0, "Native Hawaiian or Other Pacific Islander": 0, "Asian, Native Hawaiian, or Other Pacific Islander": 0}, "offenses": {"Larceny": 87, "Simple Assault": 21, "Fraud": 20, "All Other Offenses": 11, "Aggravated Assault": 6, "Burglary": 4, "Vandalism": 4, "Disorderly Conduct": 3, "Robbery": 1, "Weapons": 1, "Embezzlement": 1, "Sex Offenses": 1, "Rape (Legacy)": 1, "Counterfeiting/Forgery": 1, "Drug Sale/Manufacturing": 1}, "offense_categories": {"Larceny": 87, "Simple Assault": 21, "Fraud Offenses": 20, "All Other Offenses": 11, "Aggravated Assault": 6, "Burglary": 4, "Destruction/Damage/Vandalism of Property": 4, "Disorderly Conduct": 3, "Robbery": 1, "Embezzlement": 1, "Sex Offenses": 1, "Weapon Law Violations": 1, "Counterfeiting/Forgery": 1, "Drug/Narcotic Offenses": 1, "Sex Offenses, Non-forcible": 1}, "year": "2022", "ori": "DE0010400", "city": "Camden town, Delaware"}, "Cheswold town, Delaware": {"total_arrests": 61, "sex": {"Male": 36, "Female": 25}, "race": {"Asian": 0, "White": 23, "Unknown": 1, "Multiple": 0, "Not Specified": 0, "Black or African American": 37, "American Indian or Alaska Native": 0, "Native Hawaiian or Other Pacific Islander": 0, "Asian, Native Hawaiian, or Other Pacific Islander": 0}, "offenses": {"Fraud": 21, "All Other Offenses": 10, "Simple Assault": 9, "Vandalism": 4, "Drug Possession": 4, "Aggravated Assault": 4, "Burglary": 3, "Stolen Property": 3, "Larceny": 2, "Vagrancy": 1}, "offense_categories": {"Fraud Offenses": 21, "All Other Offenses": 10, "Simple Assault": 9, "Aggravated Assault": 4, "Drug/Narcotic Offenses": 4, "Destruction/Damage/Vandalism of Property": 4, "Burglary": 3, "Stolen Property Offenses": 3, "Larceny": 2, "Vagrancy/Loitering": 1}, "year": "2022", "ori": "DE0012600", "city": "Cheswold town, Delaware"}, "Clayton town, Delaware": {"total_arrests": 32, "sex": {"Male": 19, "Female": 13}, "race": {"Asian": 0, "White": 18, "Unknown": 1, "Multiple": 0, "Not Specified": 0, "Black or African American": 13, "American Indian or Alaska Native": 0, "Native Hawaiian or Other Pacific Islander": 0, "Asian, Native Hawaiian, or Other Pacific Islander": 0}, "offenses": {"Simple Assault": 9, "All Other Offenses": 7, "Larceny": 4, "Disorderly Conduct": 4, "Fraud": 2, "Burglary": 2, "Vandalism": 1, "Sex Offenses": 1, "Drug Possession": 1, "Aggravated Assault": 1}, "offense_categories": {"Simple Assault": 9, "All Other Offenses": 7, "Larceny": 4, "Disorderly Conduct": 4, "Burglary": 2, "Fraud Offenses": 2, "Aggravated Assault": 1, "Drug/Narcotic Offenses": 1, "Sex Offenses, Non-forcible": 1, "Destruction/Damage/Vandalism of Property": 1}, "year": "2022", "ori": "DE0010600", "city": "Clayton town, Delaware"}, "Dagsboro town, Delaware": {"total_arrests": 61, "sex": {"Male": 43, "Female": 18}, "race": {"Asian": 0, "White": 41, "Unknown": 0, "Multiple": 0, "Not Specified": 0, "Black or African American": 20, "American Indian or Alaska Native": 0, "Native Hawaiian or Other Pacific Islander": 0, "Asian, Native Hawaiian, or Other Pacific Islander": 0}, "offenses": {"Drug Possession": 17, "All Other Offenses": 13, "Fraud": 7, "Larceny": 6, "Simple Assault": 6, "Aggravated Assault": 5, "Drive Under the Influence": 3, "Burglary": 2, "Motor Vehicle Theft": 1, "Counterfeiting/Forgery": 1}, "offense_categories": {"Drug/Narcotic Offenses": 17, "All Other Offenses": 13, "Fraud Offenses": 7, "Larceny": 6, "Simple Assault": 6, "Aggravated Assault": 5, "Drive Under the Influence": 3, "Burglary": 2, "Motor Vehicle Theft": 1, "Counterfeiting/Forgery": 1}, "year": "2022", "ori": "DE0031100", "city": "Dagsboro town, Delaware"}, "Delaware City city, Delaware": {"total_arrests": 20, "sex": {"Male": 15, "Female": 5}, "race": {"Asian": 0, "White": 14, "Unknown": 0, "Multiple": 0, "Not Specified": 0, "Black or African American": 6, "American Indian or Alaska Native": 0, "Native Hawaiian or Other Pacific Islander": 0, "Asian, Native Hawaiian, or Other Pacific Islander": 0}, "offenses": {"Simple Assault": 8, "All Other Offenses": 4, "Larceny": 3, "Fraud": 2, "Disorderly Conduct": 2, "Aggravated Assault": 1}, "offense_categories": {"Simple Assault": 8, "All Other Offenses": 4, "Larceny": 3, "Fraud Offenses": 2, "Disorderly Conduct": 2, "Aggravated Assault": 1}, "year": "2022", "ori": "DE0020900", "city": "Delaware City city, Delaware"}, "Delmar town, Delaware": {"total_arrests": 31, "sex": {"Male": 20, "Female": 11}, "race": {"Asian": 0, "White": 22, "Unknown": 0, "Multiple": 0, "Not Specified": 0, "Black or African American": 9, "American Indian or Alaska Native": 0, "Native Hawaiian or Other Pacific Islander": 0, "Asian, Native Hawaiian, or Other Pacific Islander": 0}, "offenses": {"Simple Assault": 11, "All Other Offenses": 8, "Larceny": 3, "Aggravated Assault": 3, "Burglary": 2, "Fraud": 1, "Embezzlement": 1, "Motor Vehicle Theft": 1, "Offenses Against the Family and Children": 1}, "offense_categories": {"Simple Assault": 11, "All Other Offenses": 8, "Larceny": 3, "Aggravated Assault": 3, "Burglary": 2, "Embezzlement": 1, "Fraud Offenses": 1, "Motor Vehicle Theft": 1, "Family Offenses, Nonviolent": 1}, "year": "2022", "ori": "DE0030200", "city": "Delmar town, Delaware"}, "Dewey Beach town, Delaware": {"ori": null, "total_arrests": 0, "note": "skipped_small_population"}, "Dover city, Delaware": {"total_arrests": 2108, "sex": {"Male": 1543, "Female": 565}, "race": {"Asian": 3, "White": 625, "Unknown": 10, "Multiple": 0, "Not Specified": 0, "Black or African American": 1469, "American Indian or Alaska Native": 1, "Native Hawaiian or Other Pacific Islander": 0, "Asian, Native Hawaiian, or Other Pacific Islander": 0}, "offenses": {"Simple Assault": 583, "All Other Offenses": 370, "Larceny": 332, "Drug Possession": 178, "Aggravated Assault": 125, "Drug Sale/Manufacturing": 119, "Vandalism": 106, "Weapons": 66, "Stolen Property": 59, "Disorderly Conduct": 39, "Fraud": 32, "Drive Under the Influence": 20, "Robbery": 14, "Counterfeiting/Forgery": 13, "Burglary": 12, "Motor Vehicle Theft": 11, "Embezzlement": 9, "Offenses Against the Family and Children": 6, "Sex Offenses": 5, "Rape (Legacy)": 4, "Vagrancy": 2, "Arson": 1, "Manslaughter by Negligence": 1, "Curfew and Loitering Law Violations": 1}, "offense_categories": {"Simple Assault": 583, "All Other Offenses": 370, "Larceny": 332, "Drug/Narcotic Offenses": 297, "Aggravated Assault": 125, "Destruction/Damage/Vandalism of Property": 106, "Weapon Law Violations": 66, "Stolen Property Offenses": 59, "Disorderly Conduct": 39, "Fraud Offenses": 32, "Drive Under the Influence": 20, "Robbery": 14, "Counterfeiting/Forgery": 13, "Burglary": 12, "Motor Vehicle Theft": 11, "Embezzlement": 9, "Family Offenses, Nonviolent": 6, "Sex Offenses, Non-forcible": 5, "Sex Offenses": 4, "Vagrancy/Loitering": 3, "Arson": 1, "Homicide Offenses": 1}, "year": "2022", "ori": "DE0010100", "city": "Dover city, Delaware"}, "Ellendale town, Delaware": {"total_arrests": 13, "sex": {"Male": 9, "Female": 4}, "race": {"Asian": 0, "White": 8, "Unknown": 0, "Multiple": 0, "Not Specified": 0, "Black or African American": 5, "American Indian or Alaska Native": 0, "Native Hawaiian or Other Pacific Islander": 0, "Asian, Native Hawaiian, or Other Pacific Islander": 0}, "offenses": {"All Other Offenses": 5, "Fraud": 3, "Simple Assault": 2, "Larceny": 1, "Vandalism": 1, "Disorderly Conduct": 1}, "offense_categories": {"All Other Offenses": 5, "Fraud Offenses": 3, "Simple Assault": 2, "Larceny": 1, "Disorderly Conduct": 1, "Destruction/Damage/Vandalism of Property": 1}, "year": "2022", "ori": "DE0033000", "city": "Ellendale town, Delaware"}, "Elsmere town, Delaware": {"total_arrests": 116, "sex": {"Male": 98, "Female": 18}, "race": {"Asian": 0, "White": 69, "Unknown": 0, "Multiple": 0, "Not Specified": 0, "Black or African American": 47, "American Indian or Alaska Native": 0, "Native Hawaiian or Other Pacific Islander": 0, "Asian, Native Hawaiian, or Other Pacific Islander": 0}, "offenses": {"Drug Possession": 30, "Simple Assault": 24, "All Other Offenses": 19, "Fraud": 9, "Larceny": 6, "Motor Vehicle Theft": 4, "Vagrancy": 3, "Vandalism": 3, "Stolen Property": 3, "Aggravated Assault": 3, "Disorderly Conduct": 3, "Weapons": 2, "Burglary": 2, "Counterfeiting/Forgery": 2, "Sex Offenses": 1, "Rape (Legacy)": 1, "Drug Sale/Manufacturing": 1}, "offense_categories": {"Drug/Narcotic Offenses": 31, "Simple Assault": 24, "All Other Offenses": 19, "Fraud Offenses": 9, "Larceny": 6, "Motor Vehicle Theft": 4, "Aggravated Assault": 3, "Disorderly Conduct": 3, "Vagrancy/Loitering": 3, "Stolen Property Offenses": 3, "Destruction/Damage/Vandalism of Property": 3, "Burglary": 2, "Weapon Law Violations": 2, "Counterfeiting/Forgery": 2, "Sex Offenses": 1, "Sex Offenses, Non-forcible": 1}, "year": "2022", "ori": "DE0020700", "city": "Elsmere town, Delaware"}, "Farmington town, Delaware": {"ori": null, "total_arrests": 0, "note": "skipped_small_population"}, "Felton town, Delaware": {"total_arrests": 32, "sex": {"Male": 20, "Female": 12}, "race": {"Asian": 0, "White": 22, "Unknown": 0, "Multiple": 0, "Not Specified": 0, "Black or African American": 10, "American Indian or Alaska Native": 0, "Native Hawaiian or Other Pacific Islander": 0, "Asian, Native Hawaiian, or Other Pacific Islander": 0}, "offenses": {"Larceny": 8, "Simple Assault": 8, "All Other Offenses": 4, "Fraud": 3, "Drug Possession": 3, "Aggravated Assault": 3, "Burglary": 2, "Vandalism": 1}, "offense_categories": {"Larceny": 8, "Simple Assault": 8, "All Other Offenses": 4, "Fraud Offenses": 3, "Aggravated Assault": 3, "Drug/Narcotic Offenses": 3, "Burglary": 2, "Destruction/Damage/Vandalism of Property": 1}, "year": "2022", "ori": "DE0010700", "city": "Felton town, Delaware"}, "Fenwick Island town, Delaware": {"ori": null, "total_arrests": 0, "note": "skipped_small_population"}, "Frankford town, Delaware": {"total_arrests": 13, "sex": {"Male": 9, "Female": 4}, "race": {"Asian": 0, "White": 10, "Unknown": 0, "Multiple": 0, "Not Specified": 0, "Black or African American": 3, "American Indian or Alaska Native": 0, "Native Hawaiian or Other Pacific Islander": 0, "Asian, Native Hawaiian, or Other Pacific Islander": 0}, "offenses": {"All Other Offenses": 4, "Drug Possession": 3, "Disorderly Conduct": 3, "Simple Assault": 2, "Aggravated Assault": 1}, "offense_categories": {"All Other Offenses": 4, "Disorderly Conduct": 3, "Drug/Narcotic Offenses": 3, "Simple Assault": 2, "Aggravated Assault": 1}, "year": "2022", "ori": "DE0031900", "city": "Frankford town, Delaware"}, "Frederica town, Delaware": {"total_arrests": 0, "sex": {"Male": 0, "Female": 0}, "race": {"Asian": 0, "White": 0, "Unknown": 0, "Multiple": 0, "Not Specified": 0, "Black or African American": 0, "American Indian or Alaska Native": 0, "Native Hawaiian or Other Pacific Islander": 0, "Asian, Native Hawaiian, or Other Pacific Islander": 0}, "offenses": {}, "offense_categories": {}, "year": "2022", "ori": "DE0010800", "city": "Frederica town, Delaware"}, "Georgetown town, Delaware": {"total_arrests": 385, "sex": {"Male": 280, "Female": 105}, "race": {"Asian": 0, "White": 234, "Unknown": 0, "Multiple": 0, "Not Specified": 0, "Black or African American": 151, "American Indian or Alaska Native": 0, "Native Hawaiian or Other Pacific Islander": 0, "Asian, Native Hawaiian, or Other Pacific Islander": 0}, "offenses": {"Simple Assault": 107, "All Other Offenses": 102, "Larceny": 46, "Drug Possession": 25, "Aggravated Assault": 18, "Vandalism": 17, "Fraud": 15, "Counterfeiting/Forgery": 10, "Vagrancy": 8, "Disorderly Conduct": 7, "Burglary": 5, "Robbery": 4, "Motor Vehicle Theft": 4, "Drive Under the Influence": 4, "Stolen Property": 3, "Murder and Nonnegligent Homicide": 3, "Weapons": 2, "Offenses Against the Family and Children": 2, "Sex Offenses": 1, "Liquor Law Violations": 1, "Drug Sale/Manufacturing": 1}, "offense_categories": {"Simple Assault": 107, "All Other Offenses": 102, "Larceny": 46, "Drug/Narcotic Offenses": 26, "Aggravated Assault": 18, "Destruction/Damage/Vandalism of Property": 17, "Fraud Offenses": 15, "Counterfeiting/Forgery": 10, "Vagrancy/Loitering": 8, "Disorderly Conduct": 7, "Burglary": 5, "Robbery": 4, "Motor Vehicle Theft": 4, "Drive Under the Influence": 4, "Homicide Offenses": 3, "Stolen Property Offenses": 3, "Weapon Law Violations": 2, "Family Offenses, Nonviolent": 2, "Liquor Law Violations": 1, "Sex Offenses, Non-forcible": 1}, "year": "2022", "ori": "DE0031300", "city": "Georgetown town, Delaware"}, "Greenwood town, Delaware": {"total_arrests": 4, "sex": {"Male": 2, "Female": 2}, "race": {"Asian": 0, "White": 1, "Unknown": 0, "Multiple": 0, "Not Specified": 0, "Black or African American": 3, "American Indian or Alaska Native": 0, "Native Hawaiian or Other Pacific Islander": 0, "Asian, Native Hawaiian, or Other Pacific Islander": 0}, "offenses": {"All Other Offenses": 3, "Larceny": 1}, "offense_categories": {"All Other Offenses": 3, "Larceny": 1}, "year": "2022", "ori": "DE0031400", "city": "Greenwood town, Delaware"}, "Harrington city, Delaware": {"total_arrests": 150, "sex": {"Male": 100, "Female": 50}, "race": {"Asian": 0, "White": 87, "Unknown": 0, "Multiple": 0, "Not Specified": 0, "Black or African American": 63, "American Indian or Alaska Native": 0, "Native Hawaiian or Other Pacific Islander": 0, "Asian, Native Hawaiian, or Other Pacific Islander": 0}, "offenses": {"Simple Assault": 50, "All Other Offenses": 28, "Larceny": 15, "Vandalism": 13, "Drug Possession": 13, "Fraud": 6, "Aggravated Assault": 6, "Burglary": 5, "Stolen Property": 4, "Drug Sale/Manufacturing": 3, "Disorderly Conduct": 2, "Counterfeiting/Forgery": 2, "Vagrancy": 1, "Rape (Legacy)": 1, "Offenses Against the Family and Children": 1}, "offense_categories": {"Simple Assault": 50, "All Other Offenses": 28, "Drug/Narcotic Offenses": 16, "Larceny": 15, "Destruction/Damage/Vandalism of Property": 13, "Fraud Offenses": 6, "Aggravated Assault": 6, "Burglary": 5, "Stolen Property Offenses": 4, "Disorderly Conduct": 2, "Counterfeiting/Forgery": 2, "Sex Offenses": 1, "Vagrancy/Loitering": 1, "Family Offenses, Nonviolent": 1}, "year": "2022", "ori": "DE0010200", "city": "Harrington city, Delaware"}, "Houston town, Delaware": {"ori": null, "total_arrests": 0, "note": "skipped_small_population"}, "Kenton town, Delaware": {"ori": null, "total_arrests": 0, "note": "skipped_small_population"}, "Laurel town, Delaware": {"total_arrests": 350, "sex": {"Male": 233, "Female": 117}, "race": {"Asian": 0, "White": 120, "Unknown": 1, "Multiple": 0, "Not Specified": 0, "Black or African American": 229, "American Indian or Alaska Native": 0, "Native Hawaiian or Other Pacific Islander": 0, "Asian, Native Hawaiian, or Other Pacific Islander": 0}, "offenses": {"All Other Offenses": 88, "Simple Assault": 71, "Larceny": 47, "Drug Possession": 31, "Aggravated Assault": 26, "Drug Sale/Manufacturing": 16, "Vandalism": 12, "Burglary": 11, "Robbery": 8, "Fraud": 7, "Offenses Against the Family and Children": 7, "Weapons": 6, "Drive Under the Influence": 6, "Disorderly Conduct": 4, "Counterfeiting/Forgery": 3, "Rape (Legacy)": 2, "Stolen Property": 2, "Motor Vehicle Theft": 2, "Sex Offenses": 1}, "offense_categories": {"All Other Offenses": 88, "Simple Assault": 71, "Larceny": 47, "Drug/Narcotic Offenses": 47, "Aggravated Assault": 26, "Destruction/Damage/Vandalism of Property": 12, "Burglary": 11, "Robbery": 8, "Fraud Offenses": 7, "Family Offenses, Nonviolent": 7, "Weapon Law Violations": 6, "Drive Under the Influence": 6, "Disorderly Conduct": 4, "Counterfeiting/Forgery": 3, "Sex Offenses": 2, "Motor Vehicle Theft": 2, "Stolen Property Offenses": 2, "Sex Offenses, Non-forcible": 1}, "year": "2022", "ori": "DE0030300", "city": "Laurel town, Delaware"}, "Lewes city, Delaware": {"total_arrests": 38, "sex": {"Male": 28, "Female": 10}, "race": {"Asian": 0, "White": 27, "Unknown": 0, "Multiple": 0, "Not Specified": 0, "Black or African American": 11, "American Indian or Alaska Native": 0, "Native Hawaiian or Other Pacific Islander": 0, "Asian, Native Hawaiian, or Other Pacific Islander": 0}, "offenses": {"Disorderly Conduct": 7, "All Other Offenses": 5, "Fraud": 4, "Larceny": 4, "Simple Assault": 4, "Drug Possession": 3, "Aggravated Assault": 3, "Weapons": 1, "Burglary": 1, "Vandalism": 1, "Rape (Legacy)": 1, "Motor Vehicle Theft": 1, "Counterfeiting/Forgery": 1, "Drive Under the Influence": 1, "Offenses Against the Family and Children": 1}, "offense_categories": {"Disorderly Conduct": 7, "All Other Offenses": 5, "Larceny": 4, "Fraud Offenses": 4, "Simple Assault": 4, "Aggravated Assault": 3, "Drug/Narcotic Offenses": 3, "Burglary": 1, "Sex Offenses": 1, "Motor Vehicle Theft": 1, "Weapon Law Violations": 1, "Counterfeiting/Forgery": 1, "Drive Under the Influence": 1, "Family Offenses, Nonviolent": 1, "Destruction/Damage/Vandalism of Property": 1}, "year": "2022", "ori": "DE0030400", "city": "Lewes city, Delaware"}, "Little Creek town, Delaware": {"ori": null, "total_arrests": 0, "note": "skipped_small_population"}, "Magnolia town, Delaware": {"ori": null, "total_arrests": 0, "note": "skipped_small_population"}, "Middletown town, Delaware": {"total_arrests": 558, "sex": {"Male": 329, "Female": 229}, "race": {"Asian": 1, "White": 255, "Unknown": 4, "Multiple": 0, "Not Specified": 0, "Black or African American": 298, "American Indian or Alaska Native": 0, "Native Hawaiian or Other Pacific Islander": 0, "Asian, Native Hawaiian, or Other Pacific Islander": 0}, "offenses": {"Fraud": 148, "Larceny": 110, "Simple Assault": 87, "All Other Offenses": 80, "Aggravated Assault": 30, "Drug Possession": 18, "Disorderly Conduct": 15, "Vandalism": 12, "Drug Sale/Manufacturing": 9, "Robbery": 8, "Embezzlement": 7, "Stolen Property": 6, "Motor Vehicle Theft": 6, "Burglary": 5, "Weapons": 4, "Rape (Legacy)": 4, "Counterfeiting/Forgery": 3, "Drive Under the Influence": 2, "Offenses Against the Family and Children": 2, "Sex Offenses": 1, "Curfew and Loitering Law Violations": 1}, "offense_categories": {"Fraud Offenses": 148, "Larceny": 110, "Simple Assault": 87, "All Other Offenses": 80, "Aggravated Assault": 30, "Drug/Narcotic Offenses": 27, "Disorderly Conduct": 15, "Destruction/Damage/Vandalism of Property": 12, "Robbery": 8, "Embezzlement": 7, "Motor Vehicle Theft": 6, "Stolen Property Offenses": 6, "Burglary": 5, "Sex Offenses": 4, "Weapon Law Violations": 4, "Counterfeiting/Forgery": 3, "Drive Under the Influence": 2, "Family Offenses, Nonviolent": 2, "Vagrancy/Loitering": 1, "Sex Offenses, Non-forcible": 1}, "year": "2022", "ori": "DE0020200", "city": "Middletown town, Delaware"}, "Milford city, Delaware": {"total_arrests": 748, "sex": {"Male": 519, "Female": 229}, "race": {"Asian": 3, "White": 392, "Unknown": 2, "Multiple": 0, "Not Specified": 0, "Black or African American": 351, "American Indian or Alaska Native": 0, "Native Hawaiian or Other Pacific Islander": 0, "Asian, Native Hawaiian, or Other Pacific Islander": 0}, "offenses": {"All Other Offenses": 198, "Larceny": 136, "Simple Assault": 125, "Drug Possession": 81, "Fraud": 51, "Aggravated Assault": 30, "Drug Sale/Manufacturing": 23, "Vandalism": 20, "Disorderly Conduct": 12, "Drive Under the Influence": 11, "Weapons": 10, "Robbery": 8, "Counterfeiting/Forgery": 8, "Burglary": 6, "Embezzlement": 6, "Stolen Property": 6, "Motor Vehicle Theft": 5, "Offenses Against the Family and Children": 4, "Liquor Law Violations": 3, "Sex Offenses": 2, "Rape (Legacy)": 2, "Murder and Nonnegligent Homicide": 1}, "offense_categories": {"All Other Offenses": 198, "Larceny": 136, "Simple Assault": 125, "Drug/Narcotic Offenses": 104, "Fraud Offenses": 51, "Aggravated Assault": 30, "Destruction/Damage/Vandalism of Property": 20, "Disorderly Conduct": 12, "Drive Under the Influence": 11, "Weapon Law Violations": 10, "Robbery": 8, "Counterfeiting/Forgery": 8, "Burglary": 6, "Embezzlement": 6, "Stolen Property Offenses": 6, "Motor Vehicle Theft": 5, "Family Offenses, Nonviolent": 4, "Liquor Law Violations": 3, "Sex Offenses": 2, "Sex Offenses, Non-forcible": 2, "Homicide Offenses": 1}, "year": "2022", "ori": "DE0030500", "city": "Milford city, Delaware"}, "Millsboro town, Delaware": {"total_arrests": 257, "sex": {"Male": 181, "Female": 76}, "race": {"Asian": 0, "White": 136, "Unknown": 4, "Multiple": 0, "Not Specified": 0, "Black or African American": 117, "American Indian or Alaska Native": 0, "Native Hawaiian or Other Pacific Islander": 0, "Asian, Native Hawaiian, or Other Pacific Islander": 0}, "offenses": {"Simple Assault": 76, "All Other Offenses": 49, "Drug Possession": 34, "Larceny": 30, "Disorderly Conduct": 13, "Aggravated Assault": 11, "Fraud": 9, "Drug Sale/Manufacturing": 7, "Vandalism": 6, "Robbery": 3, "Stolen Property": 3, "Counterfeiting/Forgery": 3, "Drive Under the Influence": 3, "Weapons": 2, "Vagrancy": 2, "Motor Vehicle Theft": 2, "Embezzlement": 1, "Sex Offenses": 1, "Liquor Law Violations": 1, "Offenses Against the Family and Children": 1}, "offense_categories": {"Simple Assault": 76, "All Other Offenses": 49, "Drug/Narcotic Offenses": 41, "Larceny": 30, "Disorderly Conduct": 13, "Aggravated Assault": 11, "Fraud Offenses": 9, "Destruction/Damage/Vandalism of Property": 6, "Robbery": 3, "Counterfeiting/Forgery": 3, "Stolen Property Offenses": 3, "Drive Under the Influence": 3, "Vagrancy/Loitering": 2, "Motor Vehicle Theft": 2, "Weapon Law Violations": 2, "Embezzlement": 1, "Liquor Law Violations": 1, "Sex Offenses, Non-forcible": 1, "Family Offenses, Nonviolent": 1}, "year": "2022", "ori": "DE0031500", "city": "Millsboro town, Delaware"}, "Millville town, Delaware": {"ori": null, "total_arrests": 0, "note": "no_agency_match"}, "Milton town, Delaware": {"total_arrests": 58, "sex": {"Male": 44, "Female": 14}, "race": {"Asian": 0, "White": 43, "Unknown": 0, "Multiple": 0, "Not Specified": 0, "Black or African American": 15, "American Indian or Alaska Native": 0, "Native Hawaiian or Other Pacific Islander": 0, "Asian, Native Hawaiian, or Other Pacific Islander": 0}, "offenses": {"All Other Offenses": 16, "Drug Possession": 15, "Simple Assault": 10, "Fraud": 4, "Larceny": 3, "Weapons": 3, "Aggravated Assault": 2, "Drive Under the Influence": 2, "Disorderly Conduct": 1, "Drug Sale/Manufacturing": 1, "Offenses Against the Family and Children": 1}, "offense_categories": {"All Other Offenses": 16, "Drug/Narcotic Offenses": 16, "Simple Assault": 10, "Fraud Offenses": 4, "Larceny": 3, "Weapon Law Violations": 3, "Aggravated Assault": 2, "Drive Under the Influence": 2, "Disorderly Conduct": 1, "Family Offenses, Nonviolent": 1}, "year": "2022", "ori": "DE0030600", "city": "Milton town, Delaware"}, "Newark city, Delaware": {"total_arrests": 1004, "sex": {"Male": 743, "Female": 261}, "race": {"Asian": 12, "White": 726, "Unknown": 8, "Multiple": 0, "Not Specified": 0, "Black or African American": 258, "American Indian or Alaska Native": 0, "Native Hawaiian or Other Pacific Islander": 0, "Asian, Native Hawaiian, or Other Pacific Islander": 0}, "offenses": {"Liquor Law Violations": 248, "Disorderly Conduct": 202, "All Other Offenses": 144, "Simple Assault": 126, "Larceny": 63, "Drug Possession": 56, "Aggravated Assault": 38, "Vandalism": 23, "Fraud": 17, "Burglary": 14, "Drug Sale/Manufacturing": 14, "Robbery": 11, "Drive Under the Influence": 10, "Counterfeiting/Forgery": 8, "Weapons": 7, "Motor Vehicle Theft": 7, "Stolen Property": 5, "Sex Offenses": 3, "Rape (Legacy)": 3, "Offenses Against the Family and Children": 3, "Embezzlement": 1, "Prostitution and Commercialized Vice": 1}, "offense_categories": {"Liquor Law Violations": 248, "Disorderly Conduct": 202, "All Other Offenses": 144, "Simple Assault": 126, "Drug/Narcotic Offenses": 70, "Larceny": 63, "Aggravated Assault": 38, "Destruction/Damage/Vandalism of Property": 23, "Fraud Offenses": 17, "Burglary": 14, "Robbery": 11, "Drive Under the Influence": 10, "Counterfeiting/Forgery": 8, "Motor Vehicle Theft": 7, "Weapon Law Violations": 7, "Stolen Property Offenses": 5, "Sex Offenses": 3, "Sex Offenses, Non-forcible": 3, "Family Offenses, Nonviolent": 3, "Embezzlement": 1, "Prostitution Offenses": 1}, "year": "2022", "ori": "DE0020500", "city": "Newark city, Delaware"}, "New Castle city, Delaware": {"total_arrests": 212, "sex": {"Male": 152, "Female": 60}, "race": {"Asian": 0, "White": 96, "Unknown": 1, "Multiple": 0, "Not Specified": 0, "Black or African American": 115, "American Indian or Alaska Native": 0, "Native Hawaiian or Other Pacific Islander": 0, "Asian, Native Hawaiian, or Other Pacific Islander": 0}, "offenses": {"All Other Offenses": 58, "Simple Assault": 51, "Larceny": 32, "Drug Possession": 15, "Aggravated Assault": 14, "Fraud": 13, "Vandalism": 7, "Stolen Property": 4, "Counterfeiting/Forgery": 4, "Burglary": 3, "Embezzlement": 3, "Sex Offenses": 2, "Drive Under the Influence": 2, "Weapons": 1, "Disorderly Conduct": 1, "Drug Sale/Manufacturing": 1, "Offenses Against the Family and Children": 1}, "offense_categories": {"All Other Offenses": 58, "Simple Assault": 51, "Larceny": 32, "Drug/Narcotic Offenses": 16, "Aggravated Assault": 14, "Fraud Offenses": 13, "Destruction/Damage/Vandalism of Property": 7, "Counterfeiting/Forgery": 4, "Stolen Property Offenses": 4, "Burglary": 3, "Embezzlement": 3, "Drive Under the Influence": 2, "Sex Offenses, Non-forcible": 2, "Disorderly Conduct": 1, "Weapon Law Violations": 1, "Family Offenses, Nonviolent": 1}, "year": "2022", "ori": "DE0020400", "city": "New Castle city, Delaware"}, "Newport town, Delaware": {"total_arrests": 153, "sex": {"Male": 116, "Female": 37}, "race": {"Asian": 0, "White": 69, "Unknown": 0, "Multiple": 0, "Not Specified": 0, "Black or African American": 84, "American Indian or Alaska Native": 0, "Native Hawaiian or Other Pacific Islander": 0, "Asian, Native Hawaiian, or Other Pacific Islander": 0}, "offenses": {"Drug Possession": 43, "Drug Sale/Manufacturing": 27, "All Other Offenses": 24, "Simple Assault": 15, "Weapons": 9, "Stolen Property": 6, "Vandalism": 5, "Disorderly Conduct": 5, "Fraud": 4, "Larceny": 4, "Aggravated Assault": 4, "Counterfeiting/Forgery": 3, "Burglary": 2, "Drive Under the Influence": 1, "Offenses Against the Family and Children": 1}, "offense_categories": {"Drug/Narcotic Offenses": 70, "All Other Offenses": 24, "Simple Assault": 15, "Weapon Law Violations": 9, "Stolen Property Offenses": 6, "Disorderly Conduct": 5, "Destruction/Damage/Vandalism of Property": 5, "Larceny": 4, "Fraud Offenses": 4, "Aggravated Assault": 4, "Counterfeiting/Forgery": 3, "Burglary": 2, "Drive Under the Influence": 1, "Family Offenses, Nonviolent": 1}, "year": "2022", "ori": "DE0020800", "city": "Newport town, Delaware"}, "Ocean View town, Delaware": {"total_arrests": 43, "sex": {"Male": 32, "Female": 11}, "race": {"Asian": 0, "White": 34, "Unknown": 1, "Multiple": 0, "Not Specified": 0, "Black or African American": 8, "American Indian or Alaska Native": 0, "Native Hawaiian or Other Pacific Islander": 0, "Asian, Native Hawaiian, or Other Pacific Islander": 0}, "offenses": {"Drug Possession": 10, "All Other Offenses": 10, "Simple Assault": 8, "Larceny": 6, "Drug Sale/Manufacturing": 4, "Burglary": 2, "Sex Offenses": 1, "Aggravated Assault": 1, "Drive Under the Influence": 1}, "offense_categories": {"Drug/Narcotic Offenses": 14, "All Other Offenses": 10, "Simple Assault": 8, "Larceny": 6, "Burglary": 2, "Aggravated Assault": 1, "Drive Under the Influence": 1, "Sex Offenses, Non-forcible": 1}, "year": "2022", "ori": "DE0031700", "city": "Ocean View town, Delaware"}, "Odessa town, Delaware": {"ori": null, "total_arrests": 0, "note": "skipped_small_population"}, "Rehoboth Beach city, Delaware": {"total_arrests": 108, "sex": {"Male": 79, "Female": 29}, "race": {"Asian": 1, "White": 89, "Unknown": 2, "Multiple": 0, "Not Specified": 0, "Black or African American": 16, "American Indian or Alaska Native": 0, "Native Hawaiian or Other Pacific Islander": 0, "Asian, Native Hawaiian, or Other Pacific Islander": 0}, "offenses": {"Larceny": 29, "Simple Assault": 15, "All Other Offenses": 14, "Drug Possession": 11, "Liquor Law Violations": 11, "Vandalism": 9, "Aggravated Assault": 4, "Disorderly Conduct": 4, "Fraud": 2, "Robbery": 2, "Stolen Property": 2, "Drive Under the Influence": 2, "Offenses Against the Family and Children": 2, "Weapons": 1}, "offense_categories": {"Larceny": 29, "Simple Assault": 15, "All Other Offenses": 14, "Liquor Law Violations": 11, "Drug/Narcotic Offenses": 11, "Destruction/Damage/Vandalism of Property": 9, "Aggravated Assault": 4, "Disorderly Conduct": 4, "Robbery": 2, "Fraud Offenses": 2, "Stolen Property Offenses": 2, "Drive Under the Influence": 2, "Family Offenses, Nonviolent": 2, "Weapon Law Violations": 1}, "year": "2022", "ori": "DE0030700", "city": "Rehoboth Beach city, Delaware"}, "Seaford city, Delaware": {"total_arrests": 744, "sex": {"Male": 504, "Female": 240}, "race": {"Asian": 1, "White": 352, "Unknown": 1, "Multiple": 0, "Not Specified": 0, "Black or African American": 390, "American Indian or Alaska Native": 0, "Native Hawaiian or Other Pacific Islander": 0, "Asian, Native Hawaiian, or Other Pacific Islander": 0}, "offenses": {"All Other Offenses": 172, "Simple Assault": 152, "Larceny": 141, "Drug Possession": 62, "Fraud": 48, "Aggravated Assault": 42, "Vandalism": 25, "Disorderly Conduct": 24, "Drug Sale/Manufacturing": 19, "Burglary": 11, "Offenses Against the Family and Children": 10, "Weapons": 8, "Stolen Property": 6, "Counterfeiting/Forgery": 6, "Robbery": 5, "Motor Vehicle Theft": 4, "Drive Under the Influence": 4, "Vagrancy": 1, "Embezzlement": 1, "Rape (Legacy)": 1, "Liquor Law Violations": 1, "Murder and Nonnegligent Homicide": 1}, "offense_categories": {"All Other Offenses": 172, "Simple Assault": 152, "Larceny": 141, "Drug/Narcotic Offenses": 81, "Fraud Offenses": 48, "Aggravated Assault": 42, "Destruction/Damage/Vandalism of Property": 25, "Disorderly Conduct": 24, "Burglary": 11, "Family Offenses, Nonviolent": 10, "Weapon Law Violations": 8, "Counterfeiting/Forgery": 6, "Stolen Property Offenses": 6, "Robbery": 5, "Motor Vehicle Theft": 4, "Drive Under the Influence": 4, "Embezzlement": 1, "Sex Offenses": 1, "Homicide Offenses": 1, "Vagrancy/Loitering": 1, "Liquor Law Violations": 1}, "year": "2022", "ori": "DE0030800", "city": "Seaford city, Delaware"}, "Selbyville town, Delaware": {"total_arrests": 56, "sex": {"Male": 40, "Female": 16}, "race": {"Asian": 0, "White": 41, "Unknown": 0, "Multiple": 0, "Not Specified": 0, "Black or African American": 15, "American Indian or Alaska Native": 0, "Native Hawaiian or Other Pacific Islander": 0, "Asian, Native Hawaiian, or Other Pacific Islander": 0}, "offenses": {"Simple Assault": 19, "All Other Offenses": 11, "Larceny": 6, "Drug Possession": 6, "Aggravated Assault": 6, "Disorderly Conduct": 3, "Burglary": 2, "Drive Under the Influence": 2, "Counterfeiting/Forgery": 1}, "offense_categories": {"Simple Assault": 19, "All Other Offenses": 11, "Larceny": 6, "Aggravated Assault": 6, "Drug/Narcotic Offenses": 6, "Disorderly Conduct": 3, "Burglary": 2, "Drive Under the Influence": 2, "Counterfeiting/Forgery": 1}, "year": "2022", "ori": "DE0031600", "city": "Selbyville town, Delaware"}, "Slaughter Beach town, Delaware": {"ori": null, "total_arrests": 0, "note": "skipped_small_population"}, "Smyrna town, Delaware": {"total_arrests": 600, "sex": {"Male": 410, "Female": 190}, "race": {"Asian": 2, "White": 308, "Unknown": 2, "Multiple": 0, "Not Specified": 0, "Black or African American": 288, "American Indian or Alaska Native": 0, "Native Hawaiian or Other Pacific Islander": 0, "Asian, Native Hawaiian, or Other Pacific Islander": 0}, "offenses": {"All Other Offenses": 148, "Simple Assault": 122, "Drug Possession": 94, "Larceny": 50, "Fraud": 43, "Drug Sale/Manufacturing": 31, "Aggravated Assault": 25, "Disorderly Conduct": 21, "Vandalism": 14, "Drive Under the Influence": 13, "Burglary": 10, "Weapons": 8, "Stolen Property": 6, "Offenses Against the Family and Children": 4, "Motor Vehicle Theft": 3, "Counterfeiting/Forgery": 3, "Robbery": 2, "Vagrancy": 2, "Rape (Legacy)": 1}, "offense_categories": {"All Other Offenses": 148, "Drug/Narcotic Offenses": 125, "Simple Assault": 122, "Larceny": 50, "Fraud Offenses": 43, "Aggravated Assault": 25, "Disorderly Conduct": 21, "Destruction/Damage/Vandalism of Property": 14, "Drive Under the Influence": 13, "Burglary": 10, "Weapon Law Violations": 8, "Stolen Property Offenses": 6, "Family Offenses, Nonviolent": 4, "Motor Vehicle Theft": 3, "Counterfeiting/Forgery": 3, "Robbery": 2, "Vagrancy/Loitering": 2, "Sex Offenses": 1}, "year": "2022", "ori": "DE0010300", "city": "Smyrna town, Delaware"}, "South Bethany town, Delaware": {"total_arrests": 3, "sex": {"Male": 3, "Female": 0}, "race": {"Asian": 0, "White": 3, "Unknown": 0, "Multiple": 0, "Not Specified": 0, "Black or African American": 0, "American Indian or Alaska Native": 0, "Native Hawaiian or Other Pacific Islander": 0, "Asian, Native Hawaiian, or Other Pacific Islander": 0}, "offenses": {"Vandalism": 1, "Aggravated Assault": 1, "All Other Offenses": 1}, "offense_categories": {"Aggravated Assault": 1, "All Other Offenses": 1, "Destruction/Damage/Vandalism of Property": 1}, "year": "2022", "ori": "DE0031800", "city": "South Bethany town, Delaware"}, "Townsend town, Delaware": {"total_arrests": 1, "sex": {"Male": 1, "Female": 0}, "race": {"Asian": 0, "White": 0, "Unknown": 0, "Multiple": 0, "Not Specified": 0, "Black or African American": 1, "American Indian or Alaska Native": 0, "Native Hawaiian or Other Pacific Islander": 0, "Asian, Native Hawaiian, or Other Pacific Islander": 0}, "offenses": {"Simple Assault": 1}, "offense_categories": {"Simple Assault": 1}, "year": "2022", "ori": "DE0022700", "city": "Townsend town, Delaware"}, "Wilmington city, Delaware": {"total_arrests": 2738, "sex": {"Male": 1976, "Female": 762}, "race": {"Asian": 8, "White": 446, "Unknown": 8, "Multiple": 0, "Not Specified": 0, "Black or African American": 2276, "American Indian or Alaska Native": 0, "Native Hawaiian or Other Pacific Islander": 0, "Asian, Native Hawaiian, or Other Pacific Islander": 0}, "offenses": {"Simple Assault": 806, "All Other Offenses": 389, "Aggravated Assault": 280, "Drug Possession": 241, "Drug Sale/Manufacturing": 156, "Larceny": 155, "Vandalism": 150, "Disorderly Conduct": 110, "Weapons": 109, "Burglary": 76, "Robbery": 71, "Stolen Property": 68, "Fraud": 29, "Motor Vehicle Theft": 27, "Vagrancy": 12, "Drive Under the Influence": 12, "Offenses Against the Family and Children": 11, "Sex Offenses": 8, "Rape (Legacy)": 7, "Curfew and Loitering Law Violations": 7, "Counterfeiting/Forgery": 4, "Murder and Nonnegligent Homicide": 4, "Arson": 2, "Embezzlement": 2, "Liquor Law Violations": 1, "Manslaughter by Negligence": 1}, "offense_categories": {"Simple Assault": 806, "Drug/Narcotic Offenses": 397, "All Other Offenses": 389, "Aggravated Assault": 280, "Larceny": 155, "Destruction/Damage/Vandalism of Property": 150, "Disorderly Conduct": 110, "Weapon Law Violations": 109, "Burglary": 76, "Robbery": 71, "Stolen Property Offenses": 68, "Fraud Offenses": 29, "Motor Vehicle Theft": 27, "Vagrancy/Loitering": 19, "Drive Under the Influence": 12, "Family Offenses, Nonviolent": 11, "Sex Offenses, Non-forcible": 8, "Sex Offenses": 7, "Homicide Offenses": 5, "Counterfeiting/Forgery": 4, "Arson": 2, "Embezzlement": 2, "Liquor Law Violations": 1}, "year": "2022", "ori": "DE0020600", "city": "Wilmington city, Delaware"}, "Woodside town, Delaware": {"ori": null, "total_arrests": 0, "note": "skipped_small_population"}, "Wyoming town, Delaware": {"total_arrests": 16, "sex": {"Male": 12, "Female": 4}, "race": {"Asian": 0, "White": 8, "Unknown": 0, "Multiple": 0, "Not Specified": 0, "Black or African American": 8, "American Indian or Alaska Native": 0, "Native Hawaiian or Other Pacific Islander": 0, "Asian, Native Hawaiian, or Other Pacific Islander": 0}, "offenses": {"All Other Offenses": 5, "Simple Assault": 4, "Burglary": 2, "Fraud": 1, "Sex Offenses": 1, "Rape (Legacy)": 1, "Aggravated Assault": 1, "Motor Vehicle Theft": 1}, "offense_categories": {"All Other Offenses": 5, "Simple Assault": 4, "Burglary": 2, "Sex Offenses": 1, "Fraud Offenses": 1, "Aggravated Assault": 1, "Motor Vehicle Theft": 1, "Sex Offenses, Non-forcible": 1}, "year": "2022", "ori": "DE0013100", "city": "Wyoming town, Delaware"}, "Hartly town, Delaware": {"ori": null, "total_arrests": 0, "note": "skipped_small_population"}, "Henlopen Acres town, Delaware": {"ori": null, "total_arrests": 0, "note": "skipped_small_population"}, "Leipsic town, Delaware": {"ori": null, "total_arrests": 0, "note": "skipped_small_population"}, "Viola town, Delaware": {"ori": null, "total_arrests": 0, "note": "skipped_small_population"}}, "metadata": {"state": "DE", "year": "2022", "source": "FBI CDE API", "matched_cities": 36, "total_cities": 54, "no_match": 2, "api_errors": 0, "skipped_small": 16}}