{"cities": {"Billings city, Montana": {"total_arrests": 3954, "sex": {"Male": 2711, "Female": 1243}, "race": {"Asian": 8, "White": 2531, "Unknown": 48, "Multiple": 0, "Not Specified": 0, "Black or African American": 166, "American Indian or Alaska Native": 1196, "Native Hawaiian or Other Pacific Islander": 5, "Asian, Native Hawaiian, or Other Pacific Islander": 0}, "offenses": {"All Other Offenses": 912, "Simple Assault": 659, "Larceny": 656, "Drive Under the Influence": 405, "Aggravated Assault": 297, "Drug Possession": 271, "Stolen Property": 125, "Vandalism": 118, "Disorderly Conduct": 118, "Robbery": 71, "Burglary": 60, "Motor Vehicle Theft": 59, "Liquor Law Violations": 55, "Fraud": 27, "Sex Offenses": 26, "Counterfeiting/Forgery": 24, "Drug Sale/Manufacturing": 17, "Rape (Legacy)": 14, "Arson": 12, "Weapons": 11, "Offenses Against the Family and Children": 9, "Drug Abuse Violations": 4, "Murder and Nonnegligent Homicide": 3, "Vagrancy": 2, "Embezzlement": 1, "Manslaughter by Negligence": 1, "Curfew and Loitering Law Violations": 1}, "offense_categories": {"All Other Offenses": 912, "Simple Assault": 659, "Larceny": 656, "Drive Under the Influence": 405, "Aggravated Assault": 297, "Drug/Narcotic Offenses": 292, "Stolen Property Offenses": 125, "Disorderly Conduct": 118, "Destruction/Damage/Vandalism of Property": 118, "Robbery": 71, "Burglary": 60, "Motor Vehicle Theft": 59, "Liquor Law Violations": 55, "Fraud Offenses": 27, "Sex Offenses, Non-forcible": 26, "Counterfeiting/Forgery": 24, "Sex Offenses": 14, "Arson": 12, "Weapon Law Violations": 11, "Family Offenses, Nonviolent": 9, "Homicide Offenses": 4, "Vagrancy/Loitering": 3, "Embezzlement": 1}, "year": "2022", "ori": "MT0560100", "city": "Billings city, Montana"}, "Missoula city, Montana": {"total_arrests": 3541, "sex": {"Male": 2262, "Female": 1279}, "race": {"Asian": 18, "White": 2707, "Unknown": 52, "Multiple": 0, "Not Specified": 0, "Black or African American": 127, "American Indian or Alaska Native": 606, "Native Hawaiian or Other Pacific Islander": 31, "Asian, Native Hawaiian, or Other Pacific Islander": 0}, "offenses": {"Larceny": 862, "All Other Offenses": 676, "Simple Assault": 587, "Drive Under the Influence": 356, "Aggravated Assault": 188, "Disorderly Conduct": 166, "Vandalism": 136, "Drug Possession": 116, "Liquor Law Violations": 100, "Curfew and Loitering Law Violations": 69, "Fraud": 59, "Motor Vehicle Theft": 47, "Offenses Against the Family and Children": 38, "Burglary": 33, "Sex Offenses": 30, "Stolen Property": 17, "Robbery": 16, "Counterfeiting/Forgery": 15, "Rape (Legacy)": 9, "Embezzlement": 7, "Drug Sale/Manufacturing": 6, "Arson": 3, "Weapons": 2, "Murder and Nonnegligent Homicide": 2, "Prostitution and Commercialized Vice": 1}, "offense_categories": {"Larceny": 862, "All Other Offenses": 676, "Simple Assault": 587, "Drive Under the Influence": 356, "Aggravated Assault": 188, "Disorderly Conduct": 166, "Destruction/Damage/Vandalism of Property": 136, "Drug/Narcotic Offenses": 122, "Liquor Law Violations": 100, "Vagrancy/Loitering": 69, "Fraud Offenses": 59, "Motor Vehicle Theft": 47, "Family Offenses, Nonviolent": 38, "Burglary": 33, "Sex Offenses, Non-forcible": 30, "Stolen Property Offenses": 17, "Robbery": 16, "Counterfeiting/Forgery": 15, "Sex Offenses": 9, "Embezzlement": 7, "Arson": 3, "Homicide Offenses": 2, "Weapon Law Violations": 2, "Prostitution Offenses": 1}, "year": "2022", "ori": "MT0320100", "city": "Missoula city, Montana"}, "Great Falls city, Montana": {"total_arrests": 3304, "sex": {"Male": 2134, "Female": 1170}, "race": {"Asian": 35, "White": 1920, "Unknown": 92, "Multiple": 0, "Not Specified": 0, "Black or African American": 144, "American Indian or Alaska Native": 1113, "Native Hawaiian or Other Pacific Islander": 0, "Asian, Native Hawaiian, or Other Pacific Islander": 0}, "offenses": {"Larceny": 724, "All Other Offenses": 618, "Simple Assault": 578, "Disorderly Conduct": 453, "Drive Under the Influence": 209, "Drug Possession": 140, "Aggravated Assault": 123, "Vandalism": 113, "Liquor Law Violations": 111, "Burglary": 44, "Offenses Against the Family and Children": 38, "Stolen Property": 31, "Fraud": 23, "Drug Sale/Manufacturing": 21, "Motor Vehicle Theft": 16, "Counterfeiting/Forgery": 16, "Robbery": 13, "Sex Offenses": 13, "Embezzlement": 7, "Rape (Legacy)": 7, "Arson": 4, "Weapons": 1, "Manslaughter by Negligence": 1}, "offense_categories": {"Larceny": 724, "All Other Offenses": 618, "Simple Assault": 578, "Disorderly Conduct": 453, "Drive Under the Influence": 209, "Drug/Narcotic Offenses": 161, "Aggravated Assault": 123, "Destruction/Damage/Vandalism of Property": 113, "Liquor Law Violations": 111, "Burglary": 44, "Family Offenses, Nonviolent": 38, "Stolen Property Offenses": 31, "Fraud Offenses": 23, "Motor Vehicle Theft": 16, "Counterfeiting/Forgery": 16, "Robbery": 13, "Sex Offenses, Non-forcible": 13, "Embezzlement": 7, "Sex Offenses": 7, "Arson": 4, "Homicide Offenses": 1, "Weapon Law Violations": 1}, "year": "2022", "ori": "MT0070100", "city": "Great Falls city, Montana"}, "Bozeman city, Montana": {"total_arrests": 1418, "sex": {"Male": 1110, "Female": 308}, "race": {"Asian": 19, "White": 1200, "Unknown": 28, "Multiple": 0, "Not Specified": 0, "Black or African American": 66, "American Indian or Alaska Native": 105, "Native Hawaiian or Other Pacific Islander": 0, "Asian, Native Hawaiian, or Other Pacific Islander": 0}, "offenses": {"Drive Under the Influence": 320, "All Other Offenses": 308, "Simple Assault": 259, "Larceny": 139, "Disorderly Conduct": 139, "Drug Possession": 55, "Liquor Law Violations": 54, "Aggravated Assault": 42, "Vandalism": 34, "Burglary": 19, "Motor Vehicle Theft": 10, "Drug Sale/Manufacturing": 8, "Offenses Against the Family and Children": 8, "Sex Offenses": 7, "Fraud": 5, "Weapons": 4, "Stolen Property": 3, "Arson": 1, "Robbery": 1, "Rape (Legacy)": 1, "Murder and Nonnegligent Homicide": 1}, "offense_categories": {"Drive Under the Influence": 320, "All Other Offenses": 308, "Simple Assault": 259, "Larceny": 139, "Disorderly Conduct": 139, "Drug/Narcotic Offenses": 63, "Liquor Law Violations": 54, "Aggravated Assault": 42, "Destruction/Damage/Vandalism of Property": 34, "Burglary": 19, "Motor Vehicle Theft": 10, "Family Offenses, Nonviolent": 8, "Sex Offenses, Non-forcible": 7, "Fraud Offenses": 5, "Weapon Law Violations": 4, "Stolen Property Offenses": 3, "Arson": 1, "Robbery": 1, "Sex Offenses": 1, "Homicide Offenses": 1}, "year": "2022", "ori": "MT0160100", "city": "Bozeman city, Montana"}, "Helena city, Montana": {"total_arrests": 1131, "sex": {"Male": 767, "Female": 364}, "race": {"Asian": 7, "White": 967, "Unknown": 11, "Multiple": 0, "Not Specified": 0, "Black or African American": 50, "American Indian or Alaska Native": 87, "Native Hawaiian or Other Pacific Islander": 9, "Asian, Native Hawaiian, or Other Pacific Islander": 0}, "offenses": {"Simple Assault": 285, "All Other Offenses": 208, "Larceny": 163, "Drive Under the Influence": 124, "Disorderly Conduct": 94, "Aggravated Assault": 67, "Vandalism": 43, "Drug Possession": 36, "Liquor Law Violations": 34, "Sex Offenses": 21, "Motor Vehicle Theft": 14, "Burglary": 9, "Rape (Legacy)": 8, "Arson": 5, "Fraud": 5, "Offenses Against the Family and Children": 5, "Counterfeiting/Forgery": 4, "Weapons": 2, "Robbery": 1, "Embezzlement": 1, "Stolen Property": 1, "Murder and Nonnegligent Homicide": 1}, "offense_categories": {"Simple Assault": 285, "All Other Offenses": 208, "Larceny": 163, "Drive Under the Influence": 124, "Disorderly Conduct": 94, "Aggravated Assault": 67, "Destruction/Damage/Vandalism of Property": 43, "Drug/Narcotic Offenses": 36, "Liquor Law Violations": 34, "Sex Offenses, Non-forcible": 21, "Motor Vehicle Theft": 14, "Burglary": 9, "Sex Offenses": 8, "Arson": 5, "Fraud Offenses": 5, "Family Offenses, Nonviolent": 5, "Counterfeiting/Forgery": 4, "Weapon Law Violations": 2, "Robbery": 1, "Embezzlement": 1, "Homicide Offenses": 1, "Stolen Property Offenses": 1}, "year": "2022", "ori": "MT0250100", "city": "Helena city, Montana"}, "Kalispell city, Montana": {"total_arrests": 1043, "sex": {"Male": 701, "Female": 342}, "race": {"Asian": 5, "White": 958, "Unknown": 10, "Multiple": 0, "Not Specified": 0, "Black or African American": 16, "American Indian or Alaska Native": 54, "Native Hawaiian or Other Pacific Islander": 0, "Asian, Native Hawaiian, or Other Pacific Islander": 0}, "offenses": {"All Other Offenses": 349, "Larceny": 243, "Simple Assault": 116, "Drug Possession": 81, "Drive Under the Influence": 79, "Aggravated Assault": 44, "Disorderly Conduct": 35, "Vandalism": 26, "Liquor Law Violations": 23, "Burglary": 12, "Motor Vehicle Theft": 12, "Counterfeiting/Forgery": 5, "Drug Sale/Manufacturing": 5, "Stolen Property": 4, "Rape (Legacy)": 3, "Fraud": 1, "Robbery": 1, "Embezzlement": 1, "Sex Offenses": 1, "Murder and Nonnegligent Homicide": 1, "Offenses Against the Family and Children": 1}, "offense_categories": {"All Other Offenses": 349, "Larceny": 243, "Simple Assault": 116, "Drug/Narcotic Offenses": 86, "Drive Under the Influence": 79, "Aggravated Assault": 44, "Disorderly Conduct": 35, "Destruction/Damage/Vandalism of Property": 26, "Liquor Law Violations": 23, "Burglary": 12, "Motor Vehicle Theft": 12, "Counterfeiting/Forgery": 5, "Stolen Property Offenses": 4, "Sex Offenses": 3, "Robbery": 1, "Embezzlement": 1, "Fraud Offenses": 1, "Homicide Offenses": 1, "Sex Offenses, Non-forcible": 1, "Family Offenses, Nonviolent": 1}, "year": "2022", "ori": "MT0150300", "city": "Kalispell city, Montana"}, "Belgrade city, Montana": {"total_arrests": 208, "sex": {"Male": 156, "Female": 52}, "race": {"Asian": 4, "White": 195, "Unknown": 2, "Multiple": 0, "Not Specified": 0, "Black or African American": 6, "American Indian or Alaska Native": 1, "Native Hawaiian or Other Pacific Islander": 0, "Asian, Native Hawaiian, or Other Pacific Islander": 0}, "offenses": {"Drive Under the Influence": 87, "All Other Offenses": 41, "Simple Assault": 38, "Drug Possession": 14, "Aggravated Assault": 9, "Larceny": 8, "Motor Vehicle Theft": 5, "Vandalism": 2, "Disorderly Conduct": 2, "Burglary": 1, "Offenses Against the Family and Children": 1}, "offense_categories": {"Drive Under the Influence": 87, "All Other Offenses": 41, "Simple Assault": 38, "Drug/Narcotic Offenses": 14, "Aggravated Assault": 9, "Larceny": 8, "Motor Vehicle Theft": 5, "Disorderly Conduct": 2, "Destruction/Damage/Vandalism of Property": 2, "Burglary": 1, "Family Offenses, Nonviolent": 1}, "year": "2022", "ori": "MT0160200", "city": "Belgrade city, Montana"}, "Havre city, Montana": {"total_arrests": 796, "sex": {"Male": 444, "Female": 352}, "race": {"Asian": 0, "White": 225, "Unknown": 3, "Multiple": 0, "Not Specified": 0, "Black or African American": 23, "American Indian or Alaska Native": 542, "Native Hawaiian or Other Pacific Islander": 3, "Asian, Native Hawaiian, or Other Pacific Islander": 0}, "offenses": {"Larceny": 184, "Simple Assault": 168, "All Other Offenses": 107, "Disorderly Conduct": 99, "Liquor Law Violations": 51, "Drive Under the Influence": 51, "Aggravated Assault": 30, "Offenses Against the Family and Children": 25, "Vandalism": 23, "Curfew and Loitering Law Violations": 17, "Drug Possession": 13, "Motor Vehicle Theft": 8, "Robbery": 4, "Burglary": 4, "Counterfeiting/Forgery": 4, "Sex Offenses": 3, "Vagrancy": 2, "Arson": 1, "Rape (Legacy)": 1, "Drug Sale/Manufacturing": 1}, "offense_categories": {"Larceny": 184, "Simple Assault": 168, "All Other Offenses": 107, "Disorderly Conduct": 99, "Liquor Law Violations": 51, "Drive Under the Influence": 51, "Aggravated Assault": 30, "Family Offenses, Nonviolent": 25, "Destruction/Damage/Vandalism of Property": 23, "Vagrancy/Loitering": 19, "Drug/Narcotic Offenses": 14, "Motor Vehicle Theft": 8, "Robbery": 4, "Burglary": 4, "Counterfeiting/Forgery": 4, "Sex Offenses, Non-forcible": 3, "Arson": 1, "Sex Offenses": 1}, "year": "2022", "ori": "MT0210100", "city": "Havre city, Montana"}, "Livingston city, Montana": {"total_arrests": 103, "sex": {"Male": 77, "Female": 26}, "race": {"Asian": 0, "White": 96, "Unknown": 0, "Multiple": 0, "Not Specified": 0, "Black or African American": 4, "American Indian or Alaska Native": 3, "Native Hawaiian or Other Pacific Islander": 0, "Asian, Native Hawaiian, or Other Pacific Islander": 0}, "offenses": {"Simple Assault": 32, "All Other Offenses": 19, "Disorderly Conduct": 15, "Drive Under the Influence": 12, "Aggravated Assault": 8, "Larceny": 4, "Vandalism": 3, "Drug Possession": 3, "Arson": 2, "Burglary": 2, "Sex Offenses": 1, "Motor Vehicle Theft": 1, "Drug Sale/Manufacturing": 1}, "offense_categories": {"Simple Assault": 32, "All Other Offenses": 19, "Disorderly Conduct": 15, "Drive Under the Influence": 12, "Aggravated Assault": 8, "Larceny": 4, "Drug/Narcotic Offenses": 4, "Destruction/Damage/Vandalism of Property": 3, "Arson": 2, "Burglary": 2, "Motor Vehicle Theft": 1, "Sex Offenses, Non-forcible": 1}, "year": "2022", "ori": "MT0340100", "city": "Livingston city, Montana"}, "Whitefish city, Montana": {"total_arrests": 134, "sex": {"Male": 91, "Female": 43}, "race": {"Asian": 1, "White": 124, "Unknown": 6, "Multiple": 0, "Not Specified": 0, "Black or African American": 0, "American Indian or Alaska Native": 3, "Native Hawaiian or Other Pacific Islander": 0, "Asian, Native Hawaiian, or Other Pacific Islander": 0}, "offenses": {"Drive Under the Influence": 72, "Simple Assault": 16, "All Other Offenses": 12, "Disorderly Conduct": 12, "Drug Possession": 6, "Aggravated Assault": 6, "Larceny": 5, "Vandalism": 4, "Burglary": 1}, "offense_categories": {"Drive Under the Influence": 72, "Simple Assault": 16, "All Other Offenses": 12, "Disorderly Conduct": 12, "Aggravated Assault": 6, "Drug/Narcotic Offenses": 6, "Larceny": 5, "Destruction/Damage/Vandalism of Property": 4, "Burglary": 1}, "year": "2022", "ori": "MT0150200", "city": "Whitefish city, Montana"}, "Miles City city, Montana": {"total_arrests": 94, "sex": {"Male": 68, "Female": 26}, "race": {"Asian": 0, "White": 86, "Unknown": 3, "Multiple": 0, "Not Specified": 0, "Black or African American": 1, "American Indian or Alaska Native": 4, "Native Hawaiian or Other Pacific Islander": 0, "Asian, Native Hawaiian, or Other Pacific Islander": 0}, "offenses": {"Simple Assault": 31, "Disorderly Conduct": 12, "All Other Offenses": 11, "Drive Under the Influence": 11, "Larceny": 10, "Aggravated Assault": 8, "Liquor Law Violations": 7, "Vandalism": 3, "Drug Possession": 1}, "offense_categories": {"Simple Assault": 31, "Disorderly Conduct": 12, "All Other Offenses": 11, "Drive Under the Influence": 11, "Larceny": 10, "Aggravated Assault": 8, "Liquor Law Violations": 7, "Destruction/Damage/Vandalism of Property": 3, "Drug/Narcotic Offenses": 1}, "year": "2022", "ori": "MT0090100", "city": "Miles City city, Montana"}, "Laurel city, Montana": {"total_arrests": 167, "sex": {"Male": 116, "Female": 51}, "race": {"Asian": 1, "White": 145, "Unknown": 3, "Multiple": 0, "Not Specified": 0, "Black or African American": 4, "American Indian or Alaska Native": 14, "Native Hawaiian or Other Pacific Islander": 0, "Asian, Native Hawaiian, or Other Pacific Islander": 0}, "offenses": {"Drive Under the Influence": 58, "Larceny": 40, "Simple Assault": 32, "All Other Offenses": 13, "Aggravated Assault": 9, "Drug Possession": 4, "Vandalism": 3, "Disorderly Conduct": 3, "Motor Vehicle Theft": 2, "Robbery": 1, "Liquor Law Violations": 1, "Counterfeiting/Forgery": 1}, "offense_categories": {"Drive Under the Influence": 58, "Larceny": 40, "Simple Assault": 32, "All Other Offenses": 13, "Aggravated Assault": 9, "Drug/Narcotic Offenses": 4, "Disorderly Conduct": 3, "Destruction/Damage/Vandalism of Property": 3, "Motor Vehicle Theft": 2, "Robbery": 1, "Liquor Law Violations": 1, "Counterfeiting/Forgery": 1}, "year": "2022", "ori": "MT0560200", "city": "Laurel city, Montana"}, "Sidney city, Montana": {"total_arrests": 263, "sex": {"Male": 195, "Female": 68}, "race": {"Asian": 3, "White": 233, "Unknown": 1, "Multiple": 0, "Not Specified": 0, "Black or African American": 2, "American Indian or Alaska Native": 24, "Native Hawaiian or Other Pacific Islander": 0, "Asian, Native Hawaiian, or Other Pacific Islander": 0}, "offenses": {"Drive Under the Influence": 118, "Simple Assault": 49, "Drug Possession": 29, "Disorderly Conduct": 22, "All Other Offenses": 19, "Aggravated Assault": 7, "Larceny": 5, "Vandalism": 5, "Motor Vehicle Theft": 2, "Fraud": 1, "Weapons": 1, "Burglary": 1, "Sex Offenses": 1, "Rape (Legacy)": 1, "Stolen Property": 1, "Drug Sale/Manufacturing": 1}, "offense_categories": {"Drive Under the Influence": 118, "Simple Assault": 49, "Drug/Narcotic Offenses": 30, "Disorderly Conduct": 22, "All Other Offenses": 19, "Aggravated Assault": 7, "Larceny": 5, "Destruction/Damage/Vandalism of Property": 5, "Motor Vehicle Theft": 2, "Burglary": 1, "Sex Offenses": 1, "Fraud Offenses": 1, "Weapon Law Violations": 1, "Stolen Property Offenses": 1, "Sex Offenses, Non-forcible": 1}, "year": "2022", "ori": "MT0420100", "city": "Sidney city, Montana"}, "Lewistown city, Montana": {"total_arrests": 129, "sex": {"Male": 88, "Female": 41}, "race": {"Asian": 1, "White": 111, "Unknown": 7, "Multiple": 0, "Not Specified": 0, "Black or African American": 4, "American Indian or Alaska Native": 6, "Native Hawaiian or Other Pacific Islander": 0, "Asian, Native Hawaiian, or Other Pacific Islander": 0}, "offenses": {"Drive Under the Influence": 38, "Simple Assault": 22, "Disorderly Conduct": 21, "Liquor Law Violations": 16, "Stolen Property": 6, "Vandalism": 5, "Drug Possession": 5, "All Other Offenses": 5, "Curfew and Loitering Law Violations": 5, "Aggravated Assault": 3, "Fraud": 1, "Sex Offenses": 1, "Motor Vehicle Theft": 1}, "offense_categories": {"Drive Under the Influence": 38, "Simple Assault": 22, "Disorderly Conduct": 21, "Liquor Law Violations": 16, "Stolen Property Offenses": 6, "All Other Offenses": 5, "Vagrancy/Loitering": 5, "Drug/Narcotic Offenses": 5, "Destruction/Damage/Vandalism of Property": 5, "Aggravated Assault": 3, "Fraud Offenses": 1, "Motor Vehicle Theft": 1, "Sex Offenses, Non-forcible": 1}, "year": "2022", "ori": "MT0140100", "city": "Lewistown city, Montana"}, "Columbia Falls city, Montana": {"total_arrests": 209, "sex": {"Male": 127, "Female": 82}, "race": {"Asian": 0, "White": 196, "Unknown": 5, "Multiple": 0, "Not Specified": 0, "Black or African American": 0, "American Indian or Alaska Native": 8, "Native Hawaiian or Other Pacific Islander": 0, "Asian, Native Hawaiian, or Other Pacific Islander": 0}, "offenses": {"All Other Offenses": 59, "Larceny": 54, "Drive Under the Influence": 41, "Simple Assault": 28, "Aggravated Assault": 7, "Liquor Law Violations": 6, "Disorderly Conduct": 4, "Drug Possession": 3, "Arson": 2, "Vandalism": 2, "Fraud": 1, "Burglary": 1, "Rape (Legacy)": 1}, "offense_categories": {"All Other Offenses": 59, "Larceny": 54, "Drive Under the Influence": 41, "Simple Assault": 28, "Aggravated Assault": 7, "Liquor Law Violations": 6, "Disorderly Conduct": 4, "Drug/Narcotic Offenses": 3, "Arson": 2, "Destruction/Damage/Vandalism of Property": 2, "Burglary": 1, "Sex Offenses": 1, "Fraud Offenses": 1}, "year": "2022", "ori": "MT0150100", "city": "Columbia Falls city, Montana"}, "Polson city, Montana": {"total_arrests": 404, "sex": {"Male": 254, "Female": 150}, "race": {"Asian": 3, "White": 240, "Unknown": 6, "Multiple": 0, "Not Specified": 0, "Black or African American": 1, "American Indian or Alaska Native": 154, "Native Hawaiian or Other Pacific Islander": 0, "Asian, Native Hawaiian, or Other Pacific Islander": 0}, "offenses": {"Drive Under the Influence": 70, "Larceny": 66, "All Other Offenses": 53, "Simple Assault": 50, "Drug Possession": 44, "Disorderly Conduct": 34, "Liquor Law Violations": 22, "Aggravated Assault": 21, "Vandalism": 13, "Motor Vehicle Theft": 7, "Offenses Against the Family and Children": 5, "Robbery": 4, "Fraud": 3, "Sex Offenses": 3, "Counterfeiting/Forgery": 3, "Arson": 2, "Burglary": 2, "Embezzlement": 2}, "offense_categories": {"Drive Under the Influence": 70, "Larceny": 66, "All Other Offenses": 53, "Simple Assault": 50, "Drug/Narcotic Offenses": 44, "Disorderly Conduct": 34, "Liquor Law Violations": 22, "Aggravated Assault": 21, "Destruction/Damage/Vandalism of Property": 13, "Motor Vehicle Theft": 7, "Family Offenses, Nonviolent": 5, "Robbery": 4, "Fraud Offenses": 3, "Counterfeiting/Forgery": 3, "Sex Offenses, Non-forcible": 3, "Arson": 2, "Burglary": 2, "Embezzlement": 2}, "year": "2022", "ori": "MT0240100", "city": "Polson city, Montana"}, "Hamilton city, Montana": {"total_arrests": 227, "sex": {"Male": 149, "Female": 78}, "race": {"Asian": 0, "White": 203, "Unknown": 12, "Multiple": 0, "Not Specified": 0, "Black or African American": 4, "American Indian or Alaska Native": 8, "Native Hawaiian or Other Pacific Islander": 0, "Asian, Native Hawaiian, or Other Pacific Islander": 0}, "offenses": {"Drive Under the Influence": 49, "Larceny": 44, "Simple Assault": 37, "All Other Offenses": 35, "Disorderly Conduct": 20, "Vandalism": 16, "Aggravated Assault": 8, "Weapons": 6, "Liquor Law Violations": 4, "Motor Vehicle Theft": 3, "Drug Possession": 2, "Arson": 1, "Robbery": 1, "Burglary": 1}, "offense_categories": {"Drive Under the Influence": 49, "Larceny": 44, "Simple Assault": 37, "All Other Offenses": 35, "Disorderly Conduct": 20, "Destruction/Damage/Vandalism of Property": 16, "Aggravated Assault": 8, "Weapon Law Violations": 6, "Liquor Law Violations": 4, "Motor Vehicle Theft": 3, "Drug/Narcotic Offenses": 2, "Arson": 1, "Robbery": 1, "Burglary": 1}, "year": "2022", "ori": "MT0410100", "city": "Hamilton city, Montana"}, "Glendive city, Montana": {"total_arrests": 49, "sex": {"Male": 33, "Female": 16}, "race": {"Asian": 0, "White": 48, "Unknown": 0, "Multiple": 0, "Not Specified": 0, "Black or African American": 1, "American Indian or Alaska Native": 0, "Native Hawaiian or Other Pacific Islander": 0, "Asian, Native Hawaiian, or Other Pacific Islander": 0}, "offenses": {"All Other Offenses": 21, "Drive Under the Influence": 7, "Simple Assault": 5, "Drug Possession": 5, "Disorderly Conduct": 4, "Liquor Law Violations": 3, "Sex Offenses": 2, "Larceny": 1, "Vandalism": 1}, "offense_categories": {"All Other Offenses": 21, "Drive Under the Influence": 7, "Simple Assault": 5, "Drug/Narcotic Offenses": 5, "Disorderly Conduct": 4, "Liquor Law Violations": 3, "Sex Offenses, Non-forcible": 2, "Larceny": 1, "Destruction/Damage/Vandalism of Property": 1}, "year": "2022", "ori": "MT0110100", "city": "Glendive city, Montana"}, "Dillon city, Montana": {"total_arrests": 130, "sex": {"Male": 84, "Female": 46}, "race": {"Asian": 1, "White": 120, "Unknown": 1, "Multiple": 0, "Not Specified": 0, "Black or African American": 2, "American Indian or Alaska Native": 6, "Native Hawaiian or Other Pacific Islander": 0, "Asian, Native Hawaiian, or Other Pacific Islander": 0}, "offenses": {"Drive Under the Influence": 31, "All Other Offenses": 21, "Simple Assault": 17, "Disorderly Conduct": 17, "Larceny": 13, "Liquor Law Violations": 10, "Vandalism": 8, "Burglary": 5, "Aggravated Assault": 4, "Fraud": 1, "Weapons": 1, "Sex Offenses": 1, "Drug Possession": 1}, "offense_categories": {"Drive Under the Influence": 31, "All Other Offenses": 21, "Simple Assault": 17, "Disorderly Conduct": 17, "Larceny": 13, "Liquor Law Violations": 10, "Destruction/Damage/Vandalism of Property": 8, "Burglary": 5, "Aggravated Assault": 4, "Fraud Offenses": 1, "Weapon Law Violations": 1, "Drug/Narcotic Offenses": 1, "Sex Offenses, Non-forcible": 1}, "year": "2022", "ori": "MT0010100", "city": "Dillon city, Montana"}, "Hardin city, Montana": {"total_arrests": 140, "sex": {"Male": 92, "Female": 48}, "race": {"Asian": 0, "White": 13, "Unknown": 0, "Multiple": 0, "Not Specified": 0, "Black or African American": 0, "American Indian or Alaska Native": 127, "Native Hawaiian or Other Pacific Islander": 0, "Asian, Native Hawaiian, or Other Pacific Islander": 0}, "offenses": {"All Other Offenses": 85, "Larceny": 10, "Simple Assault": 9, "Disorderly Conduct": 9, "Liquor Law Violations": 7, "Drive Under the Influence": 7, "Aggravated Assault": 4, "Vandalism": 3, "Offenses Against the Family and Children": 3, "Motor Vehicle Theft": 2, "Weapons": 1}, "offense_categories": {"All Other Offenses": 85, "Larceny": 10, "Simple Assault": 9, "Disorderly Conduct": 9, "Liquor Law Violations": 7, "Drive Under the Influence": 7, "Aggravated Assault": 4, "Family Offenses, Nonviolent": 3, "Destruction/Damage/Vandalism of Property": 3, "Motor Vehicle Theft": 2, "Weapon Law Violations": 1}, "year": "2022", "ori": "MT0020400", "city": "Hardin city, Montana"}, "Glasgow city, Montana": {"total_arrests": 86, "sex": {"Male": 62, "Female": 24}, "race": {"Asian": 0, "White": 66, "Unknown": 2, "Multiple": 0, "Not Specified": 0, "Black or African American": 1, "American Indian or Alaska Native": 17, "Native Hawaiian or Other Pacific Islander": 0, "Asian, Native Hawaiian, or Other Pacific Islander": 0}, "offenses": {"Drive Under the Influence": 25, "All Other Offenses": 23, "Disorderly Conduct": 12, "Simple Assault": 11, "Rape (Legacy)": 5, "Larceny": 4, "Aggravated Assault": 3, "Drug Possession": 2, "Arson": 1}, "offense_categories": {"Drive Under the Influence": 25, "All Other Offenses": 23, "Disorderly Conduct": 12, "Simple Assault": 11, "Sex Offenses": 5, "Larceny": 4, "Aggravated Assault": 3, "Drug/Narcotic Offenses": 2, "Arson": 1}, "year": "2022", "ori": "MT0530100", "city": "Glasgow city, Montana"}, "Shelby city, Montana": {"ori": null, "total_arrests": 0, "note": "no_agency_match"}, "Cut Bank city, Montana": {"total_arrests": 176, "sex": {"Male": 106, "Female": 70}, "race": {"Asian": 0, "White": 38, "Unknown": 2, "Multiple": 0, "Not Specified": 0, "Black or African American": 0, "American Indian or Alaska Native": 136, "Native Hawaiian or Other Pacific Islander": 0, "Asian, Native Hawaiian, or Other Pacific Islander": 0}, "offenses": {"Simple Assault": 49, "Larceny": 29, "All Other Offenses": 27, "Disorderly Conduct": 17, "Vandalism": 11, "Drive Under the Influence": 10, "Drug Possession": 8, "Aggravated Assault": 8, "Burglary": 7, "Liquor Law Violations": 6, "Robbery": 2, "Motor Vehicle Theft": 2}, "offense_categories": {"Simple Assault": 49, "Larceny": 29, "All Other Offenses": 27, "Disorderly Conduct": 17, "Destruction/Damage/Vandalism of Property": 11, "Drive Under the Influence": 10, "Aggravated Assault": 8, "Drug/Narcotic Offenses": 8, "Burglary": 7, "Liquor Law Violations": 6, "Robbery": 2, "Motor Vehicle Theft": 2}, "year": "2022", "ori": "MT0180200", "city": "Cut Bank city, Montana"}, "Deer Lodge city, Montana": {"total_arrests": 63, "sex": {"Male": 45, "Female": 18}, "race": {"Asian": 0, "White": 61, "Unknown": 1, "Multiple": 0, "Not Specified": 0, "Black or African American": 0, "American Indian or Alaska Native": 1, "Native Hawaiian or Other Pacific Islander": 0, "Asian, Native Hawaiian, or Other Pacific Islander": 0}, "offenses": {"Simple Assault": 22, "All Other Offenses": 9, "Larceny": 7, "Drive Under the Influence": 6, "Aggravated Assault": 5, "Disorderly Conduct": 4, "Weapons": 2, "Vandalism": 2, "Drug Possession": 2, "Liquor Law Violations": 2, "Murder and Nonnegligent Homicide": 1, "Offenses Against the Family and Children": 1}, "offense_categories": {"Simple Assault": 22, "All Other Offenses": 9, "Larceny": 7, "Drive Under the Influence": 6, "Aggravated Assault": 5, "Disorderly Conduct": 4, "Liquor Law Violations": 2, "Weapon Law Violations": 2, "Drug/Narcotic Offenses": 2, "Destruction/Damage/Vandalism of Property": 2, "Homicide Offenses": 1, "Family Offenses, Nonviolent": 1}, "year": "2022", "ori": "MT0390100", "city": "Deer Lodge city, Montana"}, "Libby city, Montana": {"total_arrests": 47, "sex": {"Male": 32, "Female": 15}, "race": {"Asian": 0, "White": 45, "Unknown": 1, "Multiple": 0, "Not Specified": 0, "Black or African American": 1, "American Indian or Alaska Native": 0, "Native Hawaiian or Other Pacific Islander": 0, "Asian, Native Hawaiian, or Other Pacific Islander": 0}, "offenses": {"Larceny": 20, "Simple Assault": 10, "All Other Offenses": 6, "Aggravated Assault": 5, "Vandalism": 3, "Robbery": 1, "Disorderly Conduct": 1, "Counterfeiting/Forgery": 1}, "offense_categories": {"Larceny": 20, "Simple Assault": 10, "All Other Offenses": 6, "Aggravated Assault": 5, "Destruction/Damage/Vandalism of Property": 3, "Robbery": 1, "Disorderly Conduct": 1, "Counterfeiting/Forgery": 1}, "year": "2022", "ori": "MT0270100", "city": "Libby city, Montana"}, "Wolf Point city, Montana": {"total_arrests": 260, "sex": {"Male": 179, "Female": 81}, "race": {"Asian": 2, "White": 13, "Unknown": 5, "Multiple": 0, "Not Specified": 0, "Black or African American": 2, "American Indian or Alaska Native": 238, "Native Hawaiian or Other Pacific Islander": 0, "Asian, Native Hawaiian, or Other Pacific Islander": 0}, "offenses": {"Simple Assault": 78, "Disorderly Conduct": 68, "All Other Offenses": 38, "Aggravated Assault": 16, "Offenses Against the Family and Children": 12, "Larceny": 8, "Drug Possession": 8, "Liquor Law Violations": 8, "Vandalism": 7, "Burglary": 5, "Drug Sale/Manufacturing": 4, "Weapons": 3, "Sex Offenses": 3, "Robbery": 1, "Motor Vehicle Theft": 1}, "offense_categories": {"Simple Assault": 78, "Disorderly Conduct": 68, "All Other Offenses": 38, "Aggravated Assault": 16, "Drug/Narcotic Offenses": 12, "Family Offenses, Nonviolent": 12, "Larceny": 8, "Liquor Law Violations": 8, "Destruction/Damage/Vandalism of Property": 7, "Burglary": 5, "Weapon Law Violations": 3, "Sex Offenses, Non-forcible": 3, "Robbery": 1, "Motor Vehicle Theft": 1}, "year": "2022", "ori": "MT0430200", "city": "Wolf Point city, Montana"}, "Conrad city, Montana": {"total_arrests": 33, "sex": {"Male": 20, "Female": 13}, "race": {"Asian": 0, "White": 31, "Unknown": 0, "Multiple": 0, "Not Specified": 0, "Black or African American": 0, "American Indian or Alaska Native": 2, "Native Hawaiian or Other Pacific Islander": 0, "Asian, Native Hawaiian, or Other Pacific Islander": 0}, "offenses": {"Simple Assault": 13, "All Other Offenses": 7, "Aggravated Assault": 4, "Larceny": 3, "Drug Sale/Manufacturing": 3, "Burglary": 1, "Vandalism": 1, "Disorderly Conduct": 1}, "offense_categories": {"Simple Assault": 13, "All Other Offenses": 7, "Aggravated Assault": 4, "Larceny": 3, "Drug/Narcotic Offenses": 3, "Burglary": 1, "Disorderly Conduct": 1, "Destruction/Damage/Vandalism of Property": 1}, "year": "2022", "ori": "MT0370100", "city": "Conrad city, Montana"}, "Red Lodge city, Montana": {"total_arrests": 15, "sex": {"Male": 11, "Female": 4}, "race": {"Asian": 0, "White": 11, "Unknown": 1, "Multiple": 0, "Not Specified": 0, "Black or African American": 1, "American Indian or Alaska Native": 2, "Native Hawaiian or Other Pacific Islander": 0, "Asian, Native Hawaiian, or Other Pacific Islander": 0}, "offenses": {"Simple Assault": 4, "Disorderly Conduct": 3, "Liquor Law Violations": 2, "Drive Under the Influence": 2, "Rape (Legacy)": 1, "Drug Possession": 1, "Aggravated Assault": 1, "All Other Offenses": 1}, "offense_categories": {"Simple Assault": 4, "Disorderly Conduct": 3, "Liquor Law Violations": 2, "Drive Under the Influence": 2, "Sex Offenses": 1, "Aggravated Assault": 1, "All Other Offenses": 1, "Drug/Narcotic Offenses": 1}, "year": "2022", "ori": "MT0050100", "city": "Red Lodge city, Montana"}, "Townsend city, Montana": {"ori": null, "total_arrests": 0, "note": "no_agency_match"}, "Stevensville town, Montana": {"total_arrests": 4, "sex": {"Male": 3, "Female": 1}, "race": {"Asian": 0, "White": 4, "Unknown": 0, "Multiple": 0, "Not Specified": 0, "Black or African American": 0, "American Indian or Alaska Native": 0, "Native Hawaiian or Other Pacific Islander": 0, "Asian, Native Hawaiian, or Other Pacific Islander": 0}, "offenses": {"Simple Assault": 3, "All Other Offenses": 1}, "offense_categories": {"Simple Assault": 3, "All Other Offenses": 1}, "year": "2022", "ori": "MT0410200", "city": "Stevensville town, Montana"}, "Colstrip city, Montana": {"total_arrests": 17, "sex": {"Male": 13, "Female": 4}, "race": {"Asian": 0, "White": 8, "Unknown": 0, "Multiple": 0, "Not Specified": 0, "Black or African American": 0, "American Indian or Alaska Native": 9, "Native Hawaiian or Other Pacific Islander": 0, "Asian, Native Hawaiian, or Other Pacific Islander": 0}, "offenses": {"Drive Under the Influence": 7, "All Other Offenses": 3, "Vandalism": 2, "Simple Assault": 2, "Drug Possession": 1, "Aggravated Assault": 1, "Offenses Against the Family and Children": 1}, "offense_categories": {"Drive Under the Influence": 7, "All Other Offenses": 3, "Simple Assault": 2, "Destruction/Damage/Vandalism of Property": 2, "Aggravated Assault": 1, "Drug/Narcotic Offenses": 1, "Family Offenses, Nonviolent": 1}, "year": "2022", "ori": "MT0440300", "city": "Colstrip city, Montana"}, "Manhattan town, Montana": {"total_arrests": 12, "sex": {"Male": 6, "Female": 6}, "race": {"Asian": 0, "White": 12, "Unknown": 0, "Multiple": 0, "Not Specified": 0, "Black or African American": 0, "American Indian or Alaska Native": 0, "Native Hawaiian or Other Pacific Islander": 0, "Asian, Native Hawaiian, or Other Pacific Islander": 0}, "offenses": {"Larceny": 2, "Simple Assault": 2, "All Other Offenses": 2, "Drive Under the Influence": 2, "Vandalism": 1, "Aggravated Assault": 1, "Disorderly Conduct": 1, "Motor Vehicle Theft": 1}, "offense_categories": {"Larceny": 2, "Simple Assault": 2, "All Other Offenses": 2, "Drive Under the Influence": 2, "Aggravated Assault": 1, "Disorderly Conduct": 1, "Motor Vehicle Theft": 1, "Destruction/Damage/Vandalism of Property": 1}, "year": "2022", "ori": "MT0160500", "city": "Manhattan town, Montana"}, "Three Forks city, Montana": {"ori": null, "total_arrests": 0, "note": "no_agency_match"}, "Eureka town, Montana": {"total_arrests": 1, "sex": {"Male": 1, "Female": 0}, "race": {"Asian": 0, "White": 1, "Unknown": 0, "Multiple": 0, "Not Specified": 0, "Black or African American": 0, "American Indian or Alaska Native": 0, "Native Hawaiian or Other Pacific Islander": 0, "Asian, Native Hawaiian, or Other Pacific Islander": 0}, "offenses": {"Liquor Law Violations": 1}, "offense_categories": {"Liquor Law Violations": 1}, "year": "2022", "ori": "MT0270200", "city": "Eureka town, Montana"}, "Roundup city, Montana": {"ori": null, "total_arrests": 0, "note": "no_agency_match"}, "Ronan city, Montana": {"total_arrests": 95, "sex": {"Male": 56, "Female": 39}, "race": {"Asian": 0, "White": 51, "Unknown": 1, "Multiple": 0, "Not Specified": 0, "Black or African American": 1, "American Indian or Alaska Native": 42, "Native Hawaiian or Other Pacific Islander": 0, "Asian, Native Hawaiian, or Other Pacific Islander": 0}, "offenses": {"Drive Under the Influence": 28, "Simple Assault": 18, "Larceny": 14, "Drug Possession": 9, "All Other Offenses": 8, "Aggravated Assault": 5, "Disorderly Conduct": 4, "Vandalism": 2, "Liquor Law Violations": 2, "Drug Sale/Manufacturing": 2, "Burglary": 1, "Motor Vehicle Theft": 1, "Offenses Against the Family and Children": 1}, "offense_categories": {"Drive Under the Influence": 28, "Simple Assault": 18, "Larceny": 14, "Drug/Narcotic Offenses": 11, "All Other Offenses": 8, "Aggravated Assault": 5, "Disorderly Conduct": 4, "Liquor Law Violations": 2, "Destruction/Damage/Vandalism of Property": 2, "Burglary": 1, "Motor Vehicle Theft": 1, "Family Offenses, Nonviolent": 1}, "year": "2022", "ori": "MT0240200", "city": "Ronan city, Montana"}, "Columbus town, Montana": {"total_arrests": 61, "sex": {"Male": 41, "Female": 20}, "race": {"Asian": 1, "White": 58, "Unknown": 0, "Multiple": 0, "Not Specified": 0, "Black or African American": 1, "American Indian or Alaska Native": 1, "Native Hawaiian or Other Pacific Islander": 0, "Asian, Native Hawaiian, or Other Pacific Islander": 0}, "offenses": {"Drive Under the Influence": 14, "All Other Offenses": 10, "Larceny": 8, "Drug Possession": 6, "Liquor Law Violations": 6, "Simple Assault": 5, "Disorderly Conduct": 5, "Vandalism": 3, "Motor Vehicle Theft": 2, "Fraud": 1, "Aggravated Assault": 1}, "offense_categories": {"Drive Under the Influence": 14, "All Other Offenses": 10, "Larceny": 8, "Liquor Law Violations": 6, "Drug/Narcotic Offenses": 6, "Simple Assault": 5, "Disorderly Conduct": 5, "Destruction/Damage/Vandalism of Property": 3, "Motor Vehicle Theft": 2, "Fraud Offenses": 1, "Aggravated Assault": 1}, "year": "2022", "ori": "MT0480100", "city": "Columbus town, Montana"}, "Malta city, Montana": {"ori": null, "total_arrests": 0, "note": "no_agency_match"}, "East Helena city, Montana": {"total_arrests": 18, "sex": {"Male": 12, "Female": 6}, "race": {"Asian": 0, "White": 17, "Unknown": 0, "Multiple": 0, "Not Specified": 0, "Black or African American": 1, "American Indian or Alaska Native": 0, "Native Hawaiian or Other Pacific Islander": 0, "Asian, Native Hawaiian, or Other Pacific Islander": 0}, "offenses": {"All Other Offenses": 10, "Simple Assault": 4, "Drive Under the Influence": 2, "Sex Offenses": 1, "Drug Possession": 1}, "offense_categories": {"All Other Offenses": 10, "Simple Assault": 4, "Drive Under the Influence": 2, "Drug/Narcotic Offenses": 1, "Sex Offenses, Non-forcible": 1}, "year": "2022", "ori": "MT0250200", "city": "East Helena city, Montana"}, "Choteau city, Montana": {"ori": null, "total_arrests": 0, "note": "no_agency_match"}, "Forsyth city, Montana": {"ori": null, "total_arrests": 0, "note": "no_agency_match"}, "Plentywood city, Montana": {"ori": null, "total_arrests": 0, "note": "no_agency_match"}, "Thompson Falls city, Montana": {"total_arrests": 13, "sex": {"Male": 7, "Female": 6}, "race": {"Asian": 0, "White": 12, "Unknown": 1, "Multiple": 0, "Not Specified": 0, "Black or African American": 0, "American Indian or Alaska Native": 0, "Native Hawaiian or Other Pacific Islander": 0, "Asian, Native Hawaiian, or Other Pacific Islander": 0}, "offenses": {"Simple Assault": 3, "All Other Offenses": 3, "Burglary": 2, "Disorderly Conduct": 2, "Drive Under the Influence": 2, "Drug Possession": 1}, "offense_categories": {"Simple Assault": 3, "All Other Offenses": 3, "Burglary": 2, "Disorderly Conduct": 2, "Drive Under the Influence": 2, "Drug/Narcotic Offenses": 1}, "year": "2022", "ori": "MT0450300", "city": "Thompson Falls city, Montana"}, "Baker city, Montana": {"total_arrests": 26, "sex": {"Male": 18, "Female": 8}, "race": {"Asian": 0, "White": 20, "Unknown": 0, "Multiple": 0, "Not Specified": 0, "Black or African American": 0, "American Indian or Alaska Native": 6, "Native Hawaiian or Other Pacific Islander": 0, "Asian, Native Hawaiian, or Other Pacific Islander": 0}, "offenses": {"Simple Assault": 9, "All Other Offenses": 7, "Drive Under the Influence": 4, "Aggravated Assault": 2, "Liquor Law Violations": 2, "Sex Offenses": 1, "Disorderly Conduct": 1}, "offense_categories": {"Simple Assault": 9, "All Other Offenses": 7, "Drive Under the Influence": 4, "Aggravated Assault": 2, "Liquor Law Violations": 2, "Disorderly Conduct": 1, "Sex Offenses, Non-forcible": 1}, "year": "2022", "ori": "MT0130100", "city": "Baker city, Montana"}, "Big Timber city, Montana": {"ori": null, "total_arrests": 0, "note": "no_agency_match"}, "Fort Benton city, Montana": {"ori": null, "total_arrests": 0, "note": "no_agency_match"}, "Chinook city, Montana": {"total_arrests": 7, "sex": {"Male": 4, "Female": 3}, "race": {"Asian": 0, "White": 2, "Unknown": 2, "Multiple": 0, "Not Specified": 0, "Black or African American": 0, "American Indian or Alaska Native": 3, "Native Hawaiian or Other Pacific Islander": 0, "Asian, Native Hawaiian, or Other Pacific Islander": 0}, "offenses": {"All Other Offenses": 3, "Simple Assault": 2, "Disorderly Conduct": 1, "Drive Under the Influence": 1}, "offense_categories": {"All Other Offenses": 3, "Simple Assault": 2, "Disorderly Conduct": 1, "Drive Under the Influence": 1}, "year": "2022", "ori": "MT0030100", "city": "Chinook city, Montana"}, "West Yellowstone town, Montana": {"total_arrests": 35, "sex": {"Male": 25, "Female": 10}, "race": {"Asian": 3, "White": 31, "Unknown": 0, "Multiple": 0, "Not Specified": 0, "Black or African American": 1, "American Indian or Alaska Native": 0, "Native Hawaiian or Other Pacific Islander": 0, "Asian, Native Hawaiian, or Other Pacific Islander": 0}, "offenses": {"Drive Under the Influence": 15, "Liquor Law Violations": 6, "Simple Assault": 5, "Vandalism": 3, "All Other Offenses": 3, "Aggravated Assault": 2, "Sex Offenses": 1}, "offense_categories": {"Drive Under the Influence": 15, "Liquor Law Violations": 6, "Simple Assault": 5, "All Other Offenses": 3, "Destruction/Damage/Vandalism of Property": 3, "Aggravated Assault": 2, "Sex Offenses, Non-forcible": 1}, "year": "2022", "ori": "MT0160400", "city": "West Yellowstone town, Montana"}, "Boulder city, Montana": {"ori": null, "total_arrests": 0, "note": "no_agency_match"}, "Whitehall town, Montana": {"ori": null, "total_arrests": 0, "note": "no_agency_match"}, "White Sulphur Springs city, Montana": {"ori": null, "total_arrests": 0, "note": "no_agency_match"}, "Plains town, Montana": {"total_arrests": 8, "sex": {"Male": 6, "Female": 2}, "race": {"Asian": 0, "White": 8, "Unknown": 0, "Multiple": 0, "Not Specified": 0, "Black or African American": 0, "American Indian or Alaska Native": 0, "Native Hawaiian or Other Pacific Islander": 0, "Asian, Native Hawaiian, or Other Pacific Islander": 0}, "offenses": {"Simple Assault": 4, "Vandalism": 3, "Drug Possession": 1}, "offense_categories": {"Simple Assault": 4, "Destruction/Damage/Vandalism of Property": 3, "Drug/Narcotic Offenses": 1}, "year": "2022", "ori": "MT0450400", "city": "Plains town, Montana"}, "Harlowton city, Montana": {"ori": null, "total_arrests": 0, "note": "no_agency_match"}, "St. Ignatius town, Montana": {"total_arrests": 20, "sex": {"Male": 14, "Female": 6}, "race": {"Asian": 0, "White": 8, "Unknown": 3, "Multiple": 0, "Not Specified": 0, "Black or African American": 0, "American Indian or Alaska Native": 9, "Native Hawaiian or Other Pacific Islander": 0, "Asian, Native Hawaiian, or Other Pacific Islander": 0}, "offenses": {"Drive Under the Influence": 10, "Liquor Law Violations": 4, "Larceny": 2, "Sex Offenses": 1, "Simple Assault": 1, "All Other Offenses": 1, "Disorderly Conduct": 1}, "offense_categories": {"Drive Under the Influence": 10, "Liquor Law Violations": 4, "Larceny": 2, "Simple Assault": 1, "All Other Offenses": 1, "Disorderly Conduct": 1, "Sex Offenses, Non-forcible": 1}, "year": "2022", "ori": "MT0240300", "city": "St. Ignatius town, Montana"}, "Philipsburg town, Montana": {"ori": null, "total_arrests": 0, "note": "no_agency_match"}}, "metadata": {"state": "MT", "year": "2022", "source": "FBI CDE API", "matched_cities": 40, "total_cities": 55, "no_match": 15, "api_errors": 0, "skipped_small": 0}}